exasol/ai/mcp/server/__init__.py
exasol/ai/mcp/server/bucketfs_tools.py
exasol/ai/mcp/server/connection_factory.py
exasol/ai/mcp/server/db_connection.py
exasol/ai/mcp/server/generic_auth.py
exasol/ai/mcp/server/keyword_search.py
exasol/ai/mcp/server/main.py
exasol/ai/mcp/server/mcp_server.py
exasol/ai/mcp/server/meta_query.py
exasol/ai/mcp/server/named_object_pool.py
exasol/ai/mcp/server/parameter_parser.py
exasol/ai/mcp/server/parameter_pattern.py
exasol/ai/mcp/server/server_settings.py
exasol/ai/mcp/server/version.py
exasol_mcp_server-1.3.0.dist-info/LICENSE
exasol_mcp_server-1.3.0.dist-info/METADATA
exasol_mcp_server-1.3.0.dist-info/WHEEL
exasol_mcp_server-1.3.0.dist-info/entry_points.txt
exasol_mcp_server-1.3.0.dist-info/RECORD
