Metadata-Version: 2.3
Name: exasol-mcp-server
Version: 1.3.0
Summary: Exasol MCP Server
License: MIT
Keywords: exasol,MCP server
Author: Mikhail Beck
Author-email: mikhail.beck@exasol.com
Requires-Python: >=3.10,<3.14
Classifier: License :: OSI Approved :: MIT License
Classifier: Programming Language :: Python :: 3
Classifier: Programming Language :: Python :: 3.10
Classifier: Programming Language :: Python :: 3.11
Classifier: Programming Language :: Python :: 3.12
Classifier: Programming Language :: Python :: 3.13
Requires-Dist: aiofile (>=3.9.0,<4.0.0)
Requires-Dist: click (>=8.2.0,<9.0.0)
Requires-Dist: exasol-bucketfs (>=2.1.0,<3.0.0)
Requires-Dist: exasol-saas-api (>=2.4.0,<3.0.0)
Requires-Dist: fastmcp (>=2.13.0,<3.0.0)
Requires-Dist: numpy (>=2,<=2.2.0)
Requires-Dist: pathvalidate (>=3.3.1,<4.0.0)
Requires-Dist: pyexasol (>=1.0.0,<2.0.0)
Requires-Dist: rank-bm25 (>=0.2.2,<0.3.0)
Requires-Dist: sqlglot (>=27.2.0,<28.0.0)
Requires-Dist: stopwords (>=1.0.1,<2.0.0)
